{
    "id": "5b37bc49b8b9980df773b97b",
    "database": "starcards",
    "collection": "favorites",
    "schema": {
        "properties": {
            "_id": {
                "bsonType": "objectId"
            },
            "birth_year": {
                "bsonType": "String"
            },
            "class": {
                "bsonType": "String"
            },
            "classificaton": {
                "bsonType": "String"
            },
            "episode_id": {
                "bsonType": "Int32"
            },
            "eye_color": {
                "bsonType": "String"
            },
            "gender": {
                "bsonType": "String"
            },
            "manufacturer": {
                "bsonType": "String"
            },
            "model": {
                "bsonType": "String"
            },
            "name": {
                "bsonType": "String"
            },
            "population": {
                "bsonType": "Int32"
            },
            "terrain": {
                "bsonType": "String"
            },
            "title": {
                "bsonType": "String"
            },
            "url": {
                "bsonType": "String"
            }
        }
    }
}

      
    